bitmark/__init__.py
bitmark/main.py
bitmark-1.0.1.dist-info/LICENSE
bitmark-1.0.1.dist-info/METADATA
bitmark-1.0.1.dist-info/WHEEL
bitmark-1.0.1.dist-info/entry_points.txt
bitmark-1.0.1.dist-info/top_level.txt
bitmark-1.0.1.dist-info/RECORD
