Metadata-Version: 2.1
Name: bitmark
Version: 1.0.1
Summary: bitmark is a simple yet powerful utility to manage and parse bitflags represented as hexadecimal values, with support for user-defined flag sets stored in YAML files.
Author: AleirJDawn
Author-email: 
Classifier: Programming Language :: Python :: 3
Classifier: License :: OSI Approved :: MIT License
Requires-Python: >=3.6
License-File: LICENSE
Requires-Dist: pyyaml
